lambdata/__init__.py
lambdata/example_lambdata_wrangle.py
lambdata/example_oop_lambdata.py
lambdata_thecodinguru-0.2.1.dist-info/LICENSE
lambdata_thecodinguru-0.2.1.dist-info/METADATA
lambdata_thecodinguru-0.2.1.dist-info/WHEEL
lambdata_thecodinguru-0.2.1.dist-info/top_level.txt
lambdata_thecodinguru-0.2.1.dist-info/RECORD
