Metadata-Version: 2.1
Name: lambdata-thecodinguru
Version: 0.2.1
Summary: A collection of Data Science helper functions
Home-page: https://github.com/thecodinguru/lambdata
Author: thecodinguru
License: UNKNOWN
Platform: UNKNOWN
Classifier: Programming Language :: Python :: 3.6
Classifier: License :: OSI Approved :: MIT License
Classifier: Operating System :: OS Independent
Requires-Python: >=3.6
Requires-Dist: numpy
Requires-Dist: pandas
Requires-Dist: lambdata
